unknown_data/__init__.py
unknown_data/core.py
unknown_data/deploy.py
unknown_data/py.typed
unknown_data/test.py
unknown_data/utils.py
unknown_data/encoder/__init__.py
unknown_data/encoder/browser_encoder.py
unknown_data/encoder/deleted_encoder.py
unknown_data/encoder/encoder_base.py
unknown_data/encoder/lnk_encoder.py
unknown_data/encoder/messenger_encoder.py
unknown_data/encoder/prefetch_encoder.py
unknown_data/encoder/usb_encoder.py
unknown_data/loader/__init__.py
unknown_data/loader/base.py
unknown_data/loader/data.py
unknown_data/loader/loader.py
unknown_data-0.5.0.dist-info/licenses/LICENSE
unknown_data-0.5.0.dist-info/METADATA
unknown_data-0.5.0.dist-info/WHEEL
unknown_data-0.5.0.dist-info/top_level.txt
unknown_data-0.5.0.dist-info/RECORD
