Metadata-Version: 2.4
Name: unknown-data
Version: 0.5.0
Summary: A comprehensive library for parsing and processing digital forensics data artifacts with enhanced testing utilities.
Author-email: daehan00 <daehan00@github.com>
License-Expression: MIT
Project-URL: Homepage, https://github.com/daehan00/unknown_parsing_module
Project-URL: Repository, https://github.com/daehan00/unknown_parsing_module
Project-URL: Bug Tracker, https://github.com/daehan00/unknown_parsing_module/issues
Project-URL: Documentation, https://github.com/daehan00/unknown_parsing_module#readme
Keywords: forensics,data,artifacts,parsing,digital-forensics,database
Classifier: Development Status :: 4 - Beta
Classifier: Intended Audience :: Developers
Classifier: Intended Audience :: Information Technology
Classifier: Topic :: Security
Classifier: Topic :: System :: Systems Administration
Classifier: Topic :: Software Development :: Libraries :: Python Modules
Classifier: Topic :: Database
Classifier: Programming Language :: Python :: 3
Classifier: Programming Language :: Python :: 3.8
Classifier: Programming Language :: Python :: 3.9
Classifier: Programming Language :: Python :: 3.10
Classifier: Programming Language :: Python :: 3.11
Classifier: Programming Language :: Python :: 3.12
Classifier: Programming Language :: Python :: 3.13
Classifier: Operating System :: OS Independent
Requires-Python: >=3.8
License-File: LICENSE
Requires-Dist: pandas>=1.3.0
Requires-Dist: numpy
Requires-Dist: jsonschema
Requires-Dist: boto3
Requires-Dist: sqlalchemy>=2.0.0
Requires-Dist: psycopg2-binary
Provides-Extra: dev
Requires-Dist: pytest; extra == "dev"
Requires-Dist: black; extra == "dev"
Requires-Dist: mypy; extra == "dev"
Dynamic: license-file
